foxy_entities-0.0.3.dist-info/METADATA
foxy_entities-0.0.3.dist-info/WHEEL
foxy_entities-0.0.3.dist-info/entry_points.txt
foxy_entities/__init__.py
foxy_entities/abc.py
foxy_entities/exceptions.py
foxy_entities/management_entity.py
foxy_entities/py.typed
foxy_entities-0.0.3.dist-info/RECORD
