Metadata-Version: 2.1
Name: foxy-entities
Version: 0.0.3
Summary: Library for managing social media entities
Author-Email: shapdi <shapranov.work@gmail.com>
License: MIT
Requires-Python: >=3.11
Requires-Dist: pydantic>=2.12.5
